hotjb/__init__.py
hotjb/client.py
hotjb/pressuror.py
hotjb-0.1.0.dist-info/METADATA
hotjb-0.1.0.dist-info/WHEEL
hotjb-0.1.0.dist-info/top_level.txt
hotjb-0.1.0.dist-info/RECORD
