Metadata-Version: 2.1
Name: hotjb
Version: 0.1.0
Summary: yet a hotjb client.
Home-page: https://github.com/chaosannals
Author: chaosannals
Author-email: chaosannals@outlook.com
License: MIT
Platform: UNKNOWN
Requires-Dist: aiohttp (==3.7.4.post0)
